synpdu/__init__.py
synpdu/cli.py
synpdu/pdu.py
synpdu-0.2.1.dist-info/licenses/LICENSE
synpdu-0.2.1.dist-info/METADATA
synpdu-0.2.1.dist-info/WHEEL
synpdu-0.2.1.dist-info/entry_points.txt
synpdu-0.2.1.dist-info/top_level.txt
synpdu-0.2.1.dist-info/RECORD
