Metadata-Version: 2.4
Name: synpdu
Version: 0.2.1
Summary: CLI tool to control Synaccess Netbooter NP-0201DU PDU
Author: Andrew Bradford
License-Expression: GPL-2.0-only
Project-URL: Homepage, https://github.com/bradfa/synpdu
Project-URL: Issues, https://github.com/bradfa/synpdu/issues
Classifier: Development Status :: 4 - Beta
Classifier: Environment :: Console
Classifier: Intended Audience :: Developers
Classifier: Intended Audience :: System Administrators
Classifier: Operating System :: OS Independent
Classifier: Programming Language :: Python :: 3
Classifier: Programming Language :: Python :: 3.8
Classifier: Programming Language :: Python :: 3.9
Classifier: Programming Language :: Python :: 3.10
Classifier: Programming Language :: Python :: 3.11
Classifier: Programming Language :: Python :: 3.12
Classifier: Topic :: System :: Hardware
Classifier: Topic :: Utilities
Requires-Python: >=3.8
License-File: LICENSE
Provides-Extra: dev
Requires-Dist: pytest; extra == "dev"
Requires-Dist: pytest-mock; extra == "dev"
Dynamic: license-file
